namekox_zookeeper/__init__.py
namekox_zookeeper/constants.py
namekox_zookeeper/exceptions.py
namekox_zookeeper/cli/__init__.py
namekox_zookeeper/cli/subctx/__init__.py
namekox_zookeeper/cli/subctx/zookeeper.py
namekox_zookeeper/core/__init__.py
namekox_zookeeper/core/allotter.py
namekox_zookeeper/core/proxy.py
namekox_zookeeper/core/dependencies/__init__.py
namekox_zookeeper-0.0.30.dist-info/LICENSE
namekox_zookeeper-0.0.30.dist-info/METADATA
namekox_zookeeper-0.0.30.dist-info/WHEEL
namekox_zookeeper-0.0.30.dist-info/top_level.txt
namekox_zookeeper-0.0.30.dist-info/zip-safe
namekox_zookeeper-0.0.30.dist-info/RECORD
